{
  "url": "https://api.slack.com/events/channel_left",
  "type": "channel_left",
  "responce": {
    "type": "channel_left",
    "channel": "C024BE91L"
  },
  "schema": {
    "$schema": "http://json-schema.org/draft-04/schema",
    "definitions": {
      "core": {
        "type": "object",
        "definitions": {
          "subscription_type": {
            "type": "string"
          },
          "channel_id": {
            "type": "string"
          }
        }
      },
      "event_api_subscription": {
        "type": "object",
        "definitions": {
          "channel_left": {
            "type": "object",
            "properties": {
              "type": {
                "$ref": "#/definitions/core/definitions/subscription_type"
              },
              "channel": {
                "$ref": "#/definitions/core/definitions/channel_id"
              }
            }
          }
        }
      }
    }
  },
  "compatibility": [
    "RTM\n",
    "Events API\n"
  ],
  "scopes": [
    "channels:read\n"
  ]
}