{
  "url": "https://api.slack.com/events/reaction_removed",
  "type": "reaction_removed",
  "response": {
    "type": "reaction_removed",
    "user": "U024BE7LH",
    "reaction": "thumbsup",
    "item_user": "U0G9QF9C6",
    "item": {
      "type": "message",
      "channel": "C0G9QF9GZ",
      "ts": "1360782400.498405"
    },
    "event_ts": "1360782804.083113"
  },
  "schema": {
    "$schema": "http://json-schema.org/draft-07/schema",
    "definitions": {
      "user_id": {
        "type": "string"
      },
      "emoji_name": {
        "type": "string"
      },
      "reaction_item_type": {
        "type": "string"
      },
      "channel_id": {
        "type": "string"
      },
      "timestamp": {
        "type": "string"
      },
      "reaction_item": {
        "type": "object",
        "description": "(defined by script)",
        "properties": {
          "type": {
            "$ref": "#/definitions/reaction_item_type"
          },
          "channel": {
            "$ref": "#/definitions/channel_id"
          },
          "ts": {
            "$ref": "#/definitions/timestamp"
          }
        }
      },
      "reaction_removed": {
        "type": "object",
        "description": "learn more: https://api.slack.com/events/reaction_removed",
        "properties": {
          "type": {
            "const": "reaction_removed"
          },
          "user": {
            "$ref": "#/definitions/user_id"
          },
          "reaction": {
            "$ref": "#/definitions/emoji_name"
          },
          "item_user": {
            "$ref": "#/definitions/user_id"
          },
          "item": {
            "$ref": "#/definitions/reaction_item"
          },
          "event_ts": {
            "$ref": "#/definitions/timestamp"
          }
        },
        "example": {
          "type": "reaction_removed",
          "user": "U024BE7LH",
          "reaction": "thumbsup",
          "item_user": "U0G9QF9C6",
          "item": {
            "type": "message",
            "channel": "C0G9QF9GZ",
            "ts": "1360782400.498405"
          },
          "event_ts": "1360782804.083113"
        }
      }
    }
  },
  "compatibility": [
    "RTM",
    "Events API"
  ],
  "scopes": [
    "reactions:read"
  ]
}